pyCityParkingPermit/__init__.py
pyCityParkingPermit/_utils.py
pyCityParkingPermit/api.py
pyCityParkingPermit/auth.py
pyCityParkingPermit/exceptions.py
pyCityParkingPermit/models.py
pyCityParkingPermit/py.typed
pycityparkingpermit-0.3.0.dist-info/METADATA
pycityparkingpermit-0.3.0.dist-info/WHEEL
pycityparkingpermit-0.3.0.dist-info/licenses/LICENSE
pycityparkingpermit-0.3.0.dist-info/licenses/NOTICE
pycityparkingpermit-0.3.0.dist-info/RECORD
