Metadata-Version: 2.4
Name: pyCityParkingPermit
Version: 0.3.0
Summary: Async client for the CityParkingPermit parking service
Project-URL: Changelog, https://github.com/sir-Unknown/pyCityParkingPermit/blob/main/CHANGELOG.md
Project-URL: Repository, https://github.com/sir-Unknown/pyCityParkingPermit
Project-URL: Issues, https://github.com/sir-Unknown/pyCityParkingPermit/issues
Author: sir-Unknown
License: MIT License
License-File: LICENSE
License-File: NOTICE
Keywords: aiohttp,api,cityparkingpermit,parking
Classifier: Development Status :: 3 - Alpha
Classifier: Intended Audience :: Developers
Classifier: License :: OSI Approved :: MIT License
Classifier: Programming Language :: Python :: 3
Classifier: Programming Language :: Python :: 3 :: Only
Classifier: Programming Language :: Python :: 3.13
Classifier: Typing :: Typed
Requires-Python: >=3.13
Requires-Dist: aiohttp>=3.10.0
Provides-Extra: dev
Requires-Dist: build>=1.2.1; extra == 'dev'
Requires-Dist: mypy>=1.11.0; extra == 'dev'
Requires-Dist: pre-commit>=3.7.0; extra == 'dev'
Requires-Dist: ruff==0.14.10; extra == 'dev'
Requires-Dist: twine>=5.1.0; extra == 'dev'
Provides-Extra: test
Requires-Dist: aioresponses>=0.7.7; extra == 'test'
Requires-Dist: pytest-asyncio>=0.23.0; extra == 'test'
Requires-Dist: pytest>=8.3.0; extra == 'test'
